ckanext/__init__.py
ckanext/ingest/__init__.py
ckanext/ingest/artifact.py
ckanext/ingest/cli.py
ckanext/ingest/config.py
ckanext/ingest/config_declaration.yaml
ckanext/ingest/interfaces.py
ckanext/ingest/plugin.py
ckanext/ingest/record.py
ckanext/ingest/shared.py
ckanext/ingest/transform.py
ckanext/ingest/views.py
ckanext/ingest/logic/__init__.py
ckanext/ingest/logic/action.py
ckanext/ingest/logic/auth.py
ckanext/ingest/logic/schema.py
ckanext/ingest/logic/validators.py
ckanext/ingest/schemas/dataset.yaml
ckanext/ingest/strategy/__init__.py
ckanext/ingest/strategy/csv.py
ckanext/ingest/strategy/xlsx.py
ckanext/ingest/strategy/zip.py
ckanext/ingest/templates/ingest/index.html
ckanext/ingest/templates/ingest/snippets/ingest_form.html
ckanext/ingest/tests/__init__.py
ckanext/ingest/tests/test_artifact.py
ckanext/ingest/tests/test_plugin.py
ckanext/ingest/tests/test_record.py
ckanext/ingest/tests/test_registry.py
ckanext/ingest/tests/test_transform.py
ckanext/ingest/tests/logic/__init__.py
ckanext/ingest/tests/logic/test_action.py
ckanext/ingest/tests/logic/test_auth.py
ckanext/ingest/tests/logic/test_schema.py
ckanext/ingest/tests/strategy/__init__.py
ckanext/ingest/tests/strategy/test_base.py
ckanext/ingest/tests/strategy/test_csv.py
ckanext/ingest/tests/strategy/test_xlsx.py
ckanext/ingest/tests/strategy/test_zip.py
ckanext_ingest-1.4.3.dist-info/LICENSE
ckanext_ingest-1.4.3.dist-info/METADATA
ckanext_ingest-1.4.3.dist-info/WHEEL
ckanext_ingest-1.4.3.dist-info/entry_points.txt
ckanext_ingest-1.4.3.dist-info/top_level.txt
ckanext_ingest-1.4.3.dist-info/RECORD
