Metadata-Version: 2.2
Name: ckanext-ingest
Version: 1.4.3
Author-email: DataShades <datashades@linkdigital.com.au>, Sergey Motornyuk <sergey.motornyuk@linkdigital.com.au>
Maintainer-email: DataShades <datashades@linkdigital.com.au>
License: AGPL
Project-URL: Homepage, https://github.com/DataShades/ckanext-ingest
Keywords: CKAN
Classifier: Development Status :: 4 - Beta
Classifier: License :: OSI Approved :: GNU Affero General Public License v3 or later (AGPLv3+)
Classifier: Programming Language :: Python :: 3.8
Classifier: Programming Language :: Python :: 3.9
Classifier: Programming Language :: Python :: 3.10
Classifier: Programming Language :: Python :: 3.11
Requires-Python: >=3.8
License-File: LICENSE
Requires-Dist: typing_extensions
Provides-Extra: test
Requires-Dist: pytest-ckan; extra == "test"
Requires-Dist: ckanext-scheming; extra == "test"
Provides-Extra: dev
Requires-Dist: pytest-ckan; extra == "dev"
Requires-Dist: ckanext-scheming; extra == "dev"
Provides-Extra: xlsx
Requires-Dist: openpyxl; extra == "xlsx"
